raypyng_bluesky/KillRayProcesses.py
raypyng_bluesky/RaypyngOphydDevices.py
raypyng_bluesky/__init__.py
raypyng_bluesky/axes.py
raypyng_bluesky/detector.py
raypyng_bluesky/devices.py
raypyng_bluesky/positioners.py
raypyng_bluesky/preprocessor.py
raypyng_bluesky/signal.py
raypyng_bluesky/simulation_engine.py
raypyng_bluesky-1.0.0.dist-info/LICENSE
raypyng_bluesky-1.0.0.dist-info/METADATA
raypyng_bluesky-1.0.0.dist-info/WHEEL
raypyng_bluesky-1.0.0.dist-info/top_level.txt
raypyng_bluesky-1.0.0.dist-info/RECORD
