Metadata-Version: 2.1
Name: raypyng-bluesky
Version: 1.0.0
Summary: This is a raypyng-Bluesky interface library that allows using the Bluesky data acquisition framework to run raypyng simulations (RAY-UI)
Author-email: "Simone Vadilonga, Ruslan Ovsyannikov, Sebastian Sachse, Will Smith" <simone.vadilonga@helmholtz-berlin.de>
License: The MIT License (MIT)
Project-URL: Homepage, https://github.com/hz-b/raypyng-bluesky
Project-URL: Bug Tracker, https://github.com/hz-b/raypyng-bluesky/issues
Project-URL: Documentation, https://raypyng-bluesky.readthedocs.io/en/latest/index.html
Classifier: Programming Language :: Python :: 3
Classifier: License :: OSI Approved :: MIT License
Requires-Python: >=3.8
License-File: LICENSE
Requires-Dist: raypyng >=0.0.17
Requires-Dist: bluesky
Requires-Dist: ophyd
Requires-Dist: databroker
Requires-Dist: ipython
Requires-Dist: pyqt5
